{
  "descriptionHash": "00F183489A802618B8E380879E246BD4C1EF338A6A7C8A5180855FF397B1468B474FF07E54570B300B44E61C7FB468B017F834070D3AAD7D5D71FFB8971CDAA1",
  "descriptionLocation": "../../msgraph-metadata/clean_v10_openapi/openapi.yaml",
  "lockFileVersion": "1.0.0",
  "kiotaVersion": "1.10.0",
  "clientClassName": "BaseGraphServiceClient",
  "clientNamespaceName": "Microsoft.Graph",
  "language": "CSharp",
  "usesBackingStore": true,
  "excludeBackwardCompatible": false,
  "includeAdditionalData": true,
  "serializers": [
    "Microsoft.Kiota.Serialization.Json.JsonSerializationWriterFactory",
    "Microsoft.Kiota.Serialization.Text.TextSerializationWriterFactory",
    "Microsoft.Kiota.Serialization.Form.FormSerializationWriterFactory",
    "Microsoft.Kiota.Serialization.Multipart.MultipartSerializationWriterFactory"
  ],
  "deserializers": [
    "Microsoft.Kiota.Serialization.Json.JsonParseNodeFactory",
    "Microsoft.Kiota.Serialization.Text.TextParseNodeFactory",
    "Microsoft.Kiota.Serialization.Form.FormParseNodeFactory"
  ],
  "structuredMimeTypes": [
    "application/json",
    "text/plain;q=0.9",
    "application/x-www-form-urlencoded;q=0.2",
    "multipart/form-data;q=0.1"
  ],
  "includePatterns": [],
  "excludePatterns": [],
  "disabledValidationRules": []
}